nuldc/__init__.py
nuldc/commandline.py
nuldc/dump.py
nuldc/helpers.py
nuldc-0.12.0.dist-info/LICENSE
nuldc-0.12.0.dist-info/METADATA
nuldc-0.12.0.dist-info/WHEEL
nuldc-0.12.0.dist-info/entry_points.txt
nuldc-0.12.0.dist-info/RECORD
