Metadata-Version: 2.3
Name: nuldc
Version: 0.12.0
Summary: 
License: MIT
Author: davidschober
Author-email: davidschob@gmail.com
Requires-Python: >=3.8.1,<4
Classifier: License :: OSI Approved :: MIT License
Classifier: Programming Language :: Python :: 3
Classifier: Programming Language :: Python :: 3.9
Classifier: Programming Language :: Python :: 3.10
Classifier: Programming Language :: Python :: 3.11
Classifier: Programming Language :: Python :: 3.12
Classifier: Programming Language :: Python :: 3.13
Requires-Dist: autopep8 (>=2.0.1,<3.0.0)
Requires-Dist: dicttoxml (>=1.7.16,<2.0.0)
Requires-Dist: docopt (>=0.6.2,<0.7.0)
Requires-Dist: flake8 (>=6.0.0,<7.0.0)
Requires-Dist: pytest (>=7.2.0,<8.0.0)
Requires-Dist: requests (>=2.28.1,<3.0.0)
Requires-Dist: requests-mock (>=1.10.0,<2.0.0)
Requires-Dist: tqdm (>=4.64.1,<5.0.0)
Requires-Dist: typer (>=0.15.2,<0.16.0)
Requires-Dist: unicodecsv (>=0.14.1,<0.15.0)
